py621/__init__.py
py621/public.py
py621-0.0.2.dist-info/LICENSE
py621-0.0.2.dist-info/METADATA
py621-0.0.2.dist-info/WHEEL
py621-0.0.2.dist-info/top_level.txt
py621-0.0.2.dist-info/RECORD
