Metadata-Version: 2.1
Name: py621
Version: 0.0.2
Summary: A simple e621 API interface for Python
Home-page: https://github.com/BugadinhoGamers/py621
Author: Bugadinho
Author-email: miguelriechi_windows8@outlook.com
License: UNKNOWN
Platform: UNKNOWN
Classifier: Programming Language :: Python :: 3
Classifier: License :: OSI Approved :: GNU General Public License v3 (GPLv3)
Classifier: Operating System :: OS Independent
Requires-Python: >=3.6
